hydenv/__init__.py
hydenv/__main__.py
hydenv/__version__.py
hydenv/backend.py
hydenv/database.py
hydenv/exercises.py
hydenv/measurements.py
hydenv/models.py
hydenv/examples/__init__.py
hydenv/examples/_deprecated_customers.py
hydenv/examples/camels_de.py
hydenv/examples/earthquakes.py
hydenv/examples/examples.py
hydenv/examples/gpx.py
hydenv/examples/hobo.py
hydenv/examples/netatmo.py
hydenv/examples/osm.py
hydenv/examples/owm.py
hydenv/examples/raspi_logger.py
hydenv/examples/space.py
hydenv/examples/wbd.py
hydenv/exercises-js/10.c23d506f6320640913a0.js
hydenv/exercises-js/11.730c0ce01c7a613d57a0.js
hydenv/exercises-js/12.6c2407f606aa73ad6e4c.js
hydenv/exercises-js/13.e1404f660a7e4b065c49.js
hydenv/exercises-js/14.4a49edae40065a2866a9.js
hydenv/exercises-js/15.c7e2f59cd68cad204c3a.js
hydenv/exercises-js/16.112d2cf2843a1ca0aa50.js
hydenv/exercises-js/2.51cbbfce8a1ca739d698.js
hydenv/exercises-js/3.911422db2cda597ba941.js
hydenv/exercises-js/3rdpartylicenses.txt
hydenv/exercises-js/4.0ce193086b4ff8e49c1f.js
hydenv/exercises-js/8.2f0e926e7a876642687e.js
hydenv/exercises-js/9.94c97e67ce833f21f3d3.js
hydenv/exercises-js/common.d4240f020c8e6332251c.js
hydenv/exercises-js/favicon.ico
hydenv/exercises-js/index.html
hydenv/exercises-js/main.97c55ae206c8bb816142.js
hydenv/exercises-js/polyfills.19a18e9226bd3d555f07.js
hydenv/exercises-js/runtime.d9063b8dc2ed848e63ef.js
hydenv/exercises-js/scripts.3b9ab9d618b784322c5c.js
hydenv/exercises-js/styles.618cf548ba906c4592a2.css
hydenv/exercises-js/assets/logo.png
hydenv/exercises-js/assets/monaco/vs/loader.js
hydenv/exercises-js/assets/monaco/vs/base/browser/ui/codiconLabel/codicon/codicon.ttf
hydenv/exercises-js/assets/monaco/vs/base/worker/workerMain.js
hydenv/exercises-js/assets/monaco/vs/basic-languages/abap/abap.js
hydenv/exercises-js/assets/monaco/vs/basic-languages/apex/apex.js
hydenv/exercises-js/assets/monaco/vs/basic-languages/azcli/azcli.js
hydenv/exercises-js/assets/monaco/vs/basic-languages/bat/bat.js
hydenv-0.15.0.dist-info/LICENSE
hydenv-0.15.0.dist-info/METADATA
hydenv-0.15.0.dist-info/WHEEL
hydenv-0.15.0.dist-info/top_level.txt
hydenv-0.15.0.dist-info/RECORD
