Metadata-Version: 2.1
Name: hydenv
Version: 0.15.0
Summary: Database management tools for data lecture
Author: Mirko Mälicke
Author-email: mirko@hydrocode.de
License-File: LICENSE
Requires-Dist: sqlalchemy
Requires-Dist: geoalchemy2
Requires-Dist: psycopg2-binary
Requires-Dist: flask
Requires-Dist: flask-cors
Requires-Dist: fire
Requires-Dist: tabulate
Requires-Dist: tqdm
Requires-Dist: overpy
Requires-Dist: shapely <2.0,>=1.8.0
Requires-Dist: requests
Requires-Dist: beautifulsoup4
Requires-Dist: lxml
Requires-Dist: openpyxl
Requires-Dist: python-dateutil
Requires-Dist: pandas
Requires-Dist: geopandas
Requires-Dist: stdiomask
Requires-Dist: streamlit
Requires-Dist: streamlit-ace
Requires-Dist: extra-streamlit-components
Requires-Dist: universal-analytics-python3
